drf_allauthmail/__init__.py
drf_allauthmail/admin.py
drf_allauthmail/apps.py
drf_allauthmail/models.py
drf_allauthmail/serializers.py
drf_allauthmail/urls.py
drf_allauthmail/views.py
drf_allauthmail/migrations/__init__.py
drf_allauthmail/tests/__init__.py
drf_allauthmail/tests/test_serializers.py
drf_allauthmail/tests/test_views.py
drf_allauthmail-0.0.2.dist-info/METADATA
drf_allauthmail-0.0.2.dist-info/RECORD
drf_allauthmail-0.0.2.dist-info/WHEEL
drf_allauthmail-0.0.2.dist-info/top_level.txt
